base24.py
base24_builder/__init__.py
base24_builder/__main__.py
base24_builder/builder.py
base24_builder/cli.py
base24_builder/injector.py
base24_builder/shared.py
base24_builder/updater.py
base24builder-2022.dist-info/entry_points.txt
base24builder-2022.dist-info/LICENSE.md
base24builder-2022.dist-info/WHEEL
base24builder-2022.dist-info/METADATA
base24builder-2022.dist-info/RECORD
