Metadata-Version: 2.1
Name: base24builder
Version: 2022
Summary: A base 24 builder written in Python
Home-page: https://github.com/Base24/base24-builder-python
Keywords: base24
Author: Base24
Requires-Python: >=3.6,<4.0
Classifier: Intended Audience :: End Users/Desktop
Classifier: License :: OSI Approved :: MIT License
Classifier: Operating System :: OS Independent
Classifier: Programming Language :: Python :: 3
Classifier: Programming Language :: Python :: 3.10
Classifier: Programming Language :: Python :: 3.5
Classifier: Programming Language :: Python :: 3.6
Classifier: Programming Language :: Python :: 3.7
Classifier: Programming Language :: Python :: 3.8
Classifier: Programming Language :: Python :: 3.9
Requires-Dist: PyYAML (>=6.0,<7)
Requires-Dist: aiofiles (>=0.8.0,<2)
Requires-Dist: pystache (>=0.6.0,<2)
Project-URL: Documentation, https://github.com/Base24/base24-builder-python/blob/master/README.md
Project-URL: Repository, https://github.com/Base24/base24-builder-python
